u_rx.v
module u_rx #(
    parameter integer width = 8,
    parameter integer no_of_sample = 16
)(
    input wire clk,
    input wire data_in,
    input wire baud_en_rx,
    output reg rx_active = 0,
    output reg [width-1:0] data_out = 0,
    output reg rx_data_ready = 0
);

    // Durum tanımları
    localparam IDLE    = 3'd0;
    localparam START   = 3'd1;
    localparam DATA    = 3'd2;
    localparam STOP    = 3'd3;
    localparam CLEANUP = 3'd4;

    reg [2:0] state = IDLE;

    reg [3:0] sample_count = 0;
    reg [2:0] bit_index = 0;
    reg [width-1:0] rx_shift_reg = 0;

    always @(posedge clk) begin
        if (baud_en_rx) begin
            case (state)
                IDLE: begin
                    rx_data_ready <= 0;
                    sample_count <= 0;
                    bit_index <= 0;
                    rx_active <= 0;

                    if (data_in == 0) begin
                        state <= START;
                        rx_active <= 1;
                    end
                end

                START: begin
                    if (sample_count == (no_of_sample/2)) begin
                        if (data_in == 0)
                            state <= DATA;
                        else
                            state <= IDLE; // Hatalı başlangıç biti
                        sample_count <= 0;
                    end else begin
                        sample_count <= sample_count + 1;
                    end
                end

                DATA: begin
                    if (sample_count == no_of_sample - 1) begin
                        sample_count <= 0;
                        rx_shift_reg[bit_index] <= data_in;

                        if (bit_index == width - 1)
                            state <= STOP;
                        else
                            bit_index <= bit_index + 1;
                    end else begin
                        sample_count <= sample_count + 1;
                    end
                end

                STOP: begin
                    if (sample_count == no_of_sample - 1) begin
                        sample_count <= 0;
                        state <= CLEANUP;
                    end else begin
                        sample_count <= sample_count + 1;
                    end
                end

                CLEANUP: begin
                    data_out <= rx_shift_reg;
                    rx_data_ready <= 1;
                    rx_active <= 0;
                    state <= IDLE;
                end
            endcase
        end
    end
endmodule

tb_u_rx.v
`timescale 1ns / 1ps

module tb_u_rx;

    reg clk;
    reg data_in;
    reg baud_en_rx;
    wire rx_active;
    wire [7:0] data_out;
    wire rx_data_ready;

    // DUT
    u_rx uut (
        .clk(clk),
        .data_in(data_in),
        .baud_en_rx(baud_en_rx),
        .rx_active(rx_active),
        .data_out(data_out),
        .rx_data_ready(rx_data_ready)
    );

    // Clock üretimi
    always begin
        #5 clk = ~clk;
    end

    // Test senaryosu
    initial begin
        clk = 0;
        data_in = 1;
        baud_en_rx = 0;

        #20;

        // UART frame: Start (0), Data (10101010), Stop (1)
        send_uart_byte(8'b10101010);

        #200000;
        $finish;
    end

    // UART baytı gönderme prosedürü
    task send_uart_byte(input [7:0] byte);
        integer i;
        begin
            // Start bit
            @(posedge clk); data_in = 0;
            repeat (16) @(posedge clk) baud_en_rx = 1; @(posedge clk) baud_en_rx = 0;

            // Data bits (LSB first)
            for (i = 0; i < 8; i = i + 1) begin
                @(posedge clk); data_in = byte[i];
                repeat (16) @(posedge clk) baud_en_rx = 1; @(posedge clk) baud_en_rx = 0;
            end

            // Stop bit
            @(posedge clk); data_in = 1;
            repeat (16) @(posedge clk) baud_en_rx = 1; @(posedge clk) baud_en_rx = 0;
        end
    endtask

    // VCD dalga dosyası
    initial begin
        $dumpfile("wave_rx.vcd");
        $dumpvars(0, tb_u_rx);
    end

endmodule

wave_rx.vcd
$date
	Sun Apr 20 15:32:21 2025
$end
$version
	Icarus Verilog
$end
$timescale
	1ps
$end
$scope module tb_u_rx $end
$var wire 1 ! rx_data_ready $end
$var wire 1 " rx_active $end
$var wire 8 # data_out [7:0] $end
$var reg 1 $ baud_en_rx $end
$var reg 1 % clk $end
$var reg 1 & data_in $end
$scope module uut $end
$var wire 1 $ baud_en_rx $end
$var wire 1 % clk $end
$var wire 1 & data_in $end
$var parameter 3 ' CLEANUP $end
$var parameter 3 ( DATA $end
$var parameter 3 ) IDLE $end
$var parameter 3 * START $end
$var parameter 3 + STOP $end
$var parameter 32 , no_of_sample $end
$var parameter 32 - width $end
$var reg 3 . bit_index [2:0] $end
$var reg 8 / data_out [7:0] $end
$var reg 1 " rx_active $end
$var reg 1 ! rx_data_ready $end
$var reg 8 0 rx_shift_reg [7:0] $end
$var reg 4 1 sample_count [3:0] $end
$var reg 3 2 state [2:0] $end
$upscope $end
$scope task send_uart_byte $end
$var reg 8 3 byte [7:0] $end
$var integer 32 4 i [31:0] $end
$upscope $end
$upscope $end
$enddefinitions $end
$comment Show the parameter values. $end
$dumpall
b1000 -
b10000 ,
b11 +
b1 *
b0 )
b10 (
b100 '
$end
#0
$dumpvars
bx 4
bx 3
b0 2
b0 1
b0 0
b0 /
b0 .
1&
0%
0$
b0 #
0"
0!
$end
#5000
1%
#10000
0%
#15000
1%
#20000
0%
b10101010 3
#25000
0&
1%
#30000
0%
#35000
1$
1%
#40000
0%
#45000
1"
b1 2
1%
#50000
0%
#55000
b1 1
1%
#60000
0%
#65000
b10 1
1%
#70000
0%
#75000
b11 1
1%
#80000
0%
#85000
b100 1
1%
#90000
0%
#95000
b101 1
1%
#100000
0%
#105000
b110 1
1%
#110000
0%
#115000
b111 1
1%
#120000
0%
#125000
b1000 1
1%
#130000
0%
#135000
b0 1
b10 2
1%
#140000
0%
#145000
b1 1
1%
#150000
0%
#155000
b10 1
1%
#160000
0%
#165000
b11 1
1%
#170000
0%
#175000
b100 1
1%
#180000
0%
#185000
b101 1
1%
#190000
0%
#195000
b110 1
b0 4
0$
1%
#200000
0%
#205000
1%
#210000
0%
#215000
1$
1%
#220000
0%
#225000
b111 1
1%
#230000
0%
#235000
b1000 1
1%
#240000
0%
#245000
b1001 1
1%
#250000
0%
#255000
b1010 1
1%
#260000
0%
#265000
b1011 1
1%
#270000
0%
#275000
b1100 1
1%
#280000
0%
#285000
b1101 1
1%
#290000
0%
#295000
b1110 1
1%
#300000
0%
#305000
b1111 1
1%
#310000
0%
#315000
b1 .
b0 1
1%
#320000
0%
#325000
b1 1
1%
#330000
0%
#335000
b10 1
1%
#340000
0%
#345000
b11 1
1%
#350000
0%
#355000
b100 1
1%
#360000
0%
#365000
b101 1
1%
#370000
0%
#375000
b110 1
b1 4
0$
1%
#380000
0%
#385000
1&
1%
#390000
0%
#395000
1$
1%
#400000
0%
#405000
b111 1
1%
#410000
0%
#415000
b1000 1
1%
#420000
0%
#425000
b1001 1
1%
#430000
0%
#435000
b1010 1
1%
#440000
0%
#445000
b1011 1
1%
#450000
0%
#455000
b1100 1
1%
#460000
0%
#465000
b1101 1
1%
#470000
0%
#475000
b1110 1
1%
#480000
0%
#485000
b1111 1
1%
#490000
0%
#495000
b10 .
b10 0
b0 1
1%
#500000
0%
#505000
b1 1
1%
#510000
0%
#515000
b10 1
1%
#520000
0%
#525000
b11 1
1%
#530000
0%
#535000
b100 1
1%
#540000
0%
#545000
b101 1
1%
#550000
0%
#555000
b110 1
b10 4
0$
1%
#560000
0%
#565000
0&
1%
#570000
0%
#575000
1$
1%
#580000
0%
#585000
b111 1
1%
#590000
0%
#595000
b1000 1
1%
#600000
0%
#605000
b1001 1
1%
#610000
0%
#615000
b1010 1
1%
#620000
0%
#625000
b1011 1
1%
#630000
0%
#635000
b1100 1
1%
#640000
0%
#645000
b1101 1
1%
#650000
0%
#655000
b1110 1
1%
#660000
0%
#665000
b1111 1
1%
#670000
0%
#675000
b11 .
b0 1
1%
#680000
0%
#685000
b1 1
1%
#690000
0%
#695000
b10 1
1%
#700000
0%
#705000
b11 1
1%
#710000
0%
#715000
b100 1
1%
#720000
0%
#725000
b101 1
1%
#730000
0%
#735000
b110 1
b11 4
0$
1%
#740000
0%
#745000
1&
1%
#750000
0%
#755000
1$
1%
#760000
0%
#765000
b111 1
1%
#770000
0%
#775000
b1000 1
1%
#780000
0%
#785000
b1001 1
1%
#790000
0%
#795000
b1010 1
1%
#800000
0%
#805000
b1011 1
1%
#810000
0%
#815000
b1100 1
1%
#820000
0%
#825000
b1101 1
1%
#830000
0%
#835000
b1110 1
1%
#840000
0%
#845000
b1111 1
1%
#850000
0%
#855000
b100 .
b1010 0
b0 1
1%
#860000
0%
#865000
b1 1
1%
#870000
0%
#875000
b10 1
1%
#880000
0%
#885000
b11 1
1%
#890000
0%
#895000
b100 1
1%
#900000
0%
#905000
b101 1
1%
#910000
0%
#915000
b110 1
b100 4
0$
1%
#920000
0%
#925000
0&
1%
#930000
0%
#935000
1$
1%
#940000
0%
#945000
b111 1
1%
#950000
0%
#955000
b1000 1
1%
#960000
0%
#965000
b1001 1
1%
#970000
0%
#975000
b1010 1
1%
#980000
0%
#985000
b1011 1
1%
#990000
0%
#995000
b1100 1
1%
#1000000
0%
#1005000
b1101 1
1%
#1010000
0%
#1015000
b1110 1
1%
#1020000
0%
#1025000
b1111 1
1%
#1030000
0%
#1035000
b101 .
b0 1
1%
#1040000
0%
#1045000
b1 1
1%
#1050000
0%
#1055000
b10 1
1%
#1060000
0%
#1065000
b11 1
1%
#1070000
0%
#1075000
b100 1
1%
#1080000
0%
#1085000
b101 1
1%
#1090000
0%
#1095000
b110 1
b101 4
0$
1%
#1100000
0%
#1105000
1&
1%
#1110000
0%
#1115000
1$
1%
#1120000
0%
#1125000
b111 1
1%
#1130000
0%
#1135000
b1000 1
1%
#1140000
0%
#1145000
b1001 1
1%
#1150000
0%
#1155000
b1010 1
1%
#1160000
0%
#1165000
b1011 1
1%
#1170000
0%
#1175000
b1100 1
1%
#1180000
0%
#1185000
b1101 1
1%
#1190000
0%
#1195000
b1110 1
1%
#1200000
0%
#1205000
b1111 1
1%
#1210000
0%
#1215000
b110 .
b101010 0
b0 1
1%
#1220000
0%
#1225000
b1 1
1%
#1230000
0%
#1235000
b10 1
1%
#1240000
0%
#1245000
b11 1
1%
#1250000
0%
#1255000
b100 1
1%
#1260000
0%
#1265000
b101 1
1%
#1270000
0%
#1275000
b110 1
b110 4
0$
1%
#1280000
0%
#1285000
0&
1%
#1290000
0%
#1295000
1$
1%
#1300000
0%
#1305000
b111 1
1%
#1310000
0%
#1315000
b1000 1
1%
#1320000
0%
#1325000
b1001 1
1%
#1330000
0%
#1335000
b1010 1
1%
#1340000
0%
#1345000
b1011 1
1%
#1350000
0%
#1355000
b1100 1
1%
#1360000
0%
#1365000
b1101 1
1%
#1370000
0%
#1375000
b1110 1
1%
#1380000
0%
#1385000
b1111 1
1%
#1390000
0%
#1395000
b111 .
b0 1
1%
#1400000
0%
#1405000
b1 1
1%
#1410000
0%
#1415000
b10 1
1%
#1420000
0%
#1425000
b11 1
1%
#1430000
0%
#1435000
b100 1
1%
#1440000
0%
#1445000
b101 1
1%
#1450000
0%
#1455000
b110 1
b111 4
0$
1%
#1460000
0%
#1465000
1&
1%
#1470000
0%
#1475000
1$
1%
#1480000
0%
#1485000
b111 1
1%
#1490000
0%
#1495000
b1000 1
1%
#1500000
0%
#1505000
b1001 1
1%
#1510000
0%
#1515000
b1010 1
1%
#1520000
0%
#1525000
b1011 1
1%
#1530000
0%
#1535000
b1100 1
1%
#1540000
0%
#1545000
b1101 1
1%
#1550000
0%
#1555000
b1110 1
1%
#1560000
0%
#1565000
b1111 1
1%
#1570000
0%
#1575000
b11 2
b10101010 0
b0 1
1%
#1580000
0%
#1585000
b1 1
1%
#1590000
0%
#1595000
b10 1
1%
#1600000
0%
#1605000
b11 1
1%
#1610000
0%
#1615000
b100 1
1%
#1620000
0%
#1625000
b101 1
1%
#1630000
0%
#1635000
b110 1
b1000 4
0$
1%
#1640000
0%
#1645000
1%
#1650000
0%
#1655000
1$
1%
#1660000
0%
#1665000
b111 1
1%
#1670000
0%
#1675000
b1000 1
1%
#1680000
0%
#1685000
b1001 1
1%
#1690000
0%
#1695000
b1010 1
1%
#1700000
0%
#1705000
b1011 1
1%
#1710000
0%
#1715000
b1100 1
1%
#1720000
0%
#1725000
b1101 1
1%
#1730000
0%
#1735000
b1110 1
1%
#1740000
0%
#1745000
b1111 1
1%
#1750000
0%
#1755000
b100 2
b0 1
1%
#1760000
0%
#1765000
b0 2
0"
1!
b10101010 #
b10101010 /
1%
#1770000
0%
#1775000
b0 .
0!
1%
#1780000
0%
#1785000
1%
#1790000
0%
#1795000
1%
#1800000
0%
#1805000
1%
#1810000
0%
#1815000
0$
1%
